circuitpainter/__init__.py
circuitpainter/circuitpainter.py
circuitpainter/transform_matrix.py
circuitpainter-0.1.0.dist-info/LICENSE
circuitpainter-0.1.0.dist-info/WHEEL
circuitpainter-0.1.0.dist-info/METADATA
circuitpainter-0.1.0.dist-info/RECORD
