Metadata-Version: 2.3
Name: circuitpainter
Version: 0.1.0
Summary: Sketching interface for macking function printed circuit boards
Keywords: kicad,pcb,printed ciruit board,circuit design,skectching
Author-email: Matthew Mets <matt@blinkinlabs.com>
Classifier: License :: OSI Approved :: MIT License
Requires-Dist: numpy
Project-URL: Homepage, https://circuitpainter.blinkinlabs.com
Project-URL: Repository, https://github.com/blinkinlabs/circuitpainter
